PyQt5/sip.cp313-win_amd64.pyd
PyQt5_sip-12.16.0.dist-info/LICENSE
PyQt5_sip-12.16.0.dist-info/METADATA
PyQt5_sip-12.16.0.dist-info/WHEEL
PyQt5_sip-12.16.0.dist-info/top_level.txt
PyQt5_sip-12.16.0.dist-info/RECORD
