Metadata-Version: 2.1
Name: PyQt5_sip
Version: 12.16.0
Summary: The sip module support for PyQt5
Home-page: https://github.com/Python-SIP/sip
Author: Phil Thompson
Author-email: phil@riverbankcomputing.com
License: SIP
Platform: X11
Platform: macOS
Platform: Windows
Requires-Python: >=3.8
License-File: LICENSE
